step-1/verilog/ashift4_step1.v
`timescale 1ns/1ps

// Step-1 requirement: 1x4-bit input / 1x4-bit output Arithmetic Shift Circuit
// We choose: arithmetic RIGHT shift by 1 (sign-extend MSB).
// Example: A=1011 -> Y=1101
module ashift4_by1 (
    input  wire [3:0] a,
    output wire [3:0] y
);
    assign y = {a[3], a[3:1]};
endmodule

step-1/tests/tb_ashift4_by1.v
`timescale 1ns/1ps

module tb_ashift4_by1;

  reg  [3:0] A;
  wire [3:0] Y;

  integer errors;

  ashift4_by1 dut (.a(A), .y(Y));

  task check4;
    input [255:0] label;
    input [3:0] got;
    input [3:0] exp;
    begin
      if (got !== exp) begin
        $display("FAIL: %s | got=%b exp=%b", label, got, exp);
        errors = errors + 1;
      end else begin
        $display("PASS: %s", label);
      end
    end
  endtask

  initial begin
    errors = 0;

    $dumpfile("waves/ashift4_by1.vcd");
    $dumpvars(0, tb_ashift4_by1);

    // Arithmetic RIGHT shift by 1: Y = {A[3], A[3:1]}

    A = 4'b0000; #5; check4("ASR1 A=0000", Y, 4'b0000);
    A = 4'b0001; #5; check4("ASR1 A=0001", Y, 4'b0000);
    A = 4'b0010; #5; check4("ASR1 A=0010", Y, 4'b0001);
    A = 4'b0101; #5; check4("ASR1 A=0101", Y, 4'b0010);
    A = 4'b0111; #5; check4("ASR1 A=0111", Y, 4'b0011);

    // MSB=1 sign-extension cases
    A = 4'b1000; #5; check4("ASR1 A=1000", Y, 4'b1100);
    A = 4'b1001; #5; check4("ASR1 A=1001", Y, 4'b1100);
    A = 4'b1011; #5; check4("ASR1 A=1011", Y, 4'b1101);
    A = 4'b1111; #5; check4("ASR1 A=1111", Y, 4'b1111);

    if (errors == 0) $display("ASHIFT4_BY1: ALL TESTS PASSED ✅");
    else             $display("ASHIFT4_BY1: FAILED ❌ errors=%0d", errors);

    #5; $finish;
  end

endmodule

step-1/waves/ashift4_by1.vcd
$date
	Mon Feb 23 21:00:20 2026
$end
$version
	Icarus Verilog
$end
$timescale
	1ps
$end
$scope module tb_ashift4_by1 $end
$var wire 4 ! Y [3:0] $end
$var reg 4 " A [3:0] $end
$var integer 32 # errors [31:0] $end
$scope module dut $end
$var wire 4 $ a [3:0] $end
$var wire 4 % y [3:0] $end
$upscope $end
$scope task check4 $end
$var reg 4 & exp [3:0] $end
$var reg 4 ' got [3:0] $end
$var reg 256 ( label [255:0] $end
$upscope $end
$upscope $end
$enddefinitions $end
$comment Show the parameter values. $end
$dumpall
$end
#0
$dumpvars
bx (
bx '
bx &
b0 %
b0 $
b0 #
b0 "
b0 !
$end
#5000
b1 "
b1 $
b0 &
b0 '
b100000101010011010100100011000100100000010000010011110100110000001100000011000000110000 (
#10000
b1 !
b1 %
b10 "
b10 $
b100000101010011010100100011000100100000010000010011110100110000001100000011000000110001 (
#15000
b10 !
b10 %
b101 "
b101 $
b1 &
b1 '
b100000101010011010100100011000100100000010000010011110100110000001100000011000100110000 (
#20000
b11 !
b11 %
b111 "
b111 $
b10 &
b10 '
b100000101010011010100100011000100100000010000010011110100110000001100010011000000110001 (
#25000
b1100 !
b1100 %
b1000 "
b1000 $
b11 &
b11 '
b100000101010011010100100011000100100000010000010011110100110000001100010011000100110001 (
#30000
b1001 "
b1001 $
b1100 &
b1100 '
b100000101010011010100100011000100100000010000010011110100110001001100000011000000110000 (
#35000
b1101 !
b1101 %
b1011 "
b1011 $
b100000101010011010100100011000100100000010000010011110100110001001100000011000000110001 (
#40000
b1111 !
b1111 %
b1111 "
b1111 $
b1101 &
b1101 '
b100000101010011010100100011000100100000010000010011110100110001001100000011000100110001 (
#45000
b1111 &
b1111 '
b100000101010011010100100011000100100000010000010011110100110001001100010011000100110001 (
