step-1/verilog/ashift4_step1.v
`timescale 1ns/1ps

// Step-1 requirement: 1x4-bit input / 1x4-bit output Arithmetic Shift Circuit
// We choose: arithmetic RIGHT shift by 1 (sign-extend MSB).
// Example: A=1011 -> Y=1101
module ashift4_by1 (
    input  wire [3:0] a,
    output wire [3:0] y
);
    assign y = {a[3], a[3:1]};
endmodule

step-1/verilog/gates_step1.v
`timescale 1ns/1ps

// 1-bit NOT gate
module not1 (
    input  wire a,
    output wire y
);
    assign y = ~a;
endmodule

// 1-bit NAND gate
module nand1 (
    input  wire a,
    input  wire b,
    output wire y
);
    assign y = ~(a & b);
endmodule

// 1-bit NOR gate
module nor1 (
    input  wire a,
    input  wire b,
    output wire y
);
    assign y = ~(a | b);
endmodule

step-1/tests/tb_step1.v
`timescale 1ns/1ps

module tb_step1;

    // Inputs for gates
    reg a, b;
    wire y_not, y_nand, y_nor;

    // Input for shifter
    reg  [3:0] A;
    wire [3:0] Y;

    integer errors;

    // DUTs
    not1       u_not   (.a(a), .y(y_not));
    nand1      u_nand  (.a(a), .b(b), .y(y_nand));
    nor1       u_nor   (.a(a), .b(b), .y(y_nor));
    ashift4_by1 u_shft (.a(A), .y(Y));

    // Simple checker task
    task check;
        input [255:0] label;
        input [31:0] got;
        input [31:0] exp;
        begin
            if (got !== exp) begin
                $display("FAIL: %s | got=%0d (0x%0h) exp=%0d (0x%0h)",
                         label, got, got, exp, exp);
                errors = errors + 1;
            end else begin
                $display("PASS: %s", label);
            end
        end
    endtask

    initial begin
        errors = 0;

        // Dump waveforms to your waves/ folder
        $dumpfile("waves/step1.vcd");
        $dumpvars(0, tb_step1);

        // -------------------------
        // NOT gate tests
        // -------------------------
        $display("\n=== Testing NOT ===");
        a = 0; #1; check("NOT a=0", y_not, 1);
        a = 1; #1; check("NOT a=1", y_not, 0);

        // -------------------------
        // NAND gate truth table tests
        // -------------------------
        $display("\n=== Testing NAND ===");
        a = 0; b = 0; #1; check("NAND 0,0", y_nand, 1);
        a = 0; b = 1; #1; check("NAND 0,1", y_nand, 1);
        a = 1; b = 0; #1; check("NAND 1,0", y_nand, 1);
        a = 1; b = 1; #1; check("NAND 1,1", y_nand, 0);

        // -------------------------
        // NOR gate truth table tests
        // -------------------------
        $display("\n=== Testing NOR ===");
        a = 0; b = 0; #1; check("NOR 0,0", y_nor, 1);
        a = 0; b = 1; #1; check("NOR 0,1", y_nor, 0);
        a = 1; b = 0; #1; check("NOR 1,0", y_nor, 0);
        a = 1; b = 1; #1; check("NOR 1,1", y_nor, 0);

        // -------------------------
        // Arithmetic shift by 1 tests (ASR1)
        // Y = {A[3], A[3:1]}
        // -------------------------
        $display("\n=== Testing 4-bit Arithmetic RIGHT Shift by 1 (ASR1) ===");

        A = 4'b0000; #1; check("ASR1 A=0000", Y, 4'b0000);
        A = 4'b0001; #1; check("ASR1 A=0001", Y, 4'b0000);
        A = 4'b0010; #1; check("ASR1 A=0010", Y, 4'b0001);
        A = 4'b0101; #1; check("ASR1 A=0101", Y, 4'b0010);
        A = 4'b0111; #1; check("ASR1 A=0111", Y, 4'b0011);

        // MSB=1 cases show sign-extension
        A = 4'b1000; #1; check("ASR1 A=1000", Y, 4'b1100);
        A = 4'b1001; #1; check("ASR1 A=1001", Y, 4'b1100);
        A = 4'b1011; #1; check("ASR1 A=1011", Y, 4'b1101);
        A = 4'b1111; #1; check("ASR1 A=1111", Y, 4'b1111);

        // Summary
        $display("\n=== TEST SUMMARY ===");
        if (errors == 0) $display("ALL TESTS PASSED ✅");
        else             $display("TESTS FAILED ❌ errors=%0d", errors);

        #5;
        $finish;
    end

endmodule

step-1/waves/step1.vcd
$date
	Mon Feb 23 13:30:06 2026
$end
$version
	Icarus Verilog
$end
$timescale
	1ps
$end
$scope module tb_step1 $end
$var wire 1 ! y_not $end
$var wire 1 " y_nor $end
$var wire 1 # y_nand $end
$var wire 4 $ Y [3:0] $end
$var reg 4 % A [3:0] $end
$var reg 1 & a $end
$var reg 1 ' b $end
$var integer 32 ( errors [31:0] $end
$scope module u_nand $end
$var wire 1 & a $end
$var wire 1 ' b $end
$var wire 1 # y $end
$upscope $end
$scope module u_nor $end
$var wire 1 & a $end
$var wire 1 ' b $end
$var wire 1 " y $end
$upscope $end
$scope module u_not $end
$var wire 1 & a $end
$var wire 1 ! y $end
$upscope $end
$scope module u_shft $end
$var wire 4 ) a [3:0] $end
$var wire 4 * y [3:0] $end
$upscope $end
$scope task check $end
$var reg 32 + exp [31:0] $end
$var reg 32 , got [31:0] $end
$var reg 256 - label [255:0] $end
$upscope $end
$upscope $end
$enddefinitions $end
$comment Show the parameter values. $end
$dumpall
$end
#0
$dumpvars
bx -
bx ,
bx +
bx *
bx )
b0 (
x'
0&
bx %
bx $
1#
x"
1!
$end
#1000
x#
0"
0!
1&
b1 +
b1 ,
b1001110010011110101010000100000011000010011110100110000 -
#2000
1#
1"
1!
0'
0&
b0 +
b0 ,
b1001110010011110101010000100000011000010011110100110001 -
#3000
0"
1'
b1 +
b1 ,
b100111001000001010011100100010000100000001100000010110000110000 -
#4000
0!
0'
1&
b100111001000001010011100100010000100000001100000010110000110001 -
#5000
0#
1'
b100111001000001010011100100010000100000001100010010110000110000 -
#6000
1#
1"
1!
0'
0&
b0 +
b0 ,
b100111001000001010011100100010000100000001100010010110000110001 -
#7000
0"
1'
b1 +
b1 ,
b1001110010011110101001000100000001100000010110000110000 -
#8000
0!
0'
1&
b0 +
b0 ,
b1001110010011110101001000100000001100000010110000110001 -
#9000
0#
1'
b1001110010011110101001000100000001100010010110000110000 -
#10000
b0 $
b0 *
b0 %
b0 )
b1001110010011110101001000100000001100010010110000110001 -
#11000
b1 %
b1 )
b100000101010011010100100011000100100000010000010011110100110000001100000011000000110000 -
#12000
b1 $
b1 *
b10 %
b10 )
b100000101010011010100100011000100100000010000010011110100110000001100000011000000110001 -
#13000
b10 $
b10 *
b101 %
b101 )
b1 +
b1 ,
b100000101010011010100100011000100100000010000010011110100110000001100000011000100110000 -
#14000
b11 $
b11 *
b111 %
b111 )
b10 +
b10 ,
b100000101010011010100100011000100100000010000010011110100110000001100010011000000110001 -
#15000
b1100 $
b1100 *
b1000 %
b1000 )
b11 +
b11 ,
b100000101010011010100100011000100100000010000010011110100110000001100010011000100110001 -
#16000
b1001 %
b1001 )
b1100 +
b1100 ,
b100000101010011010100100011000100100000010000010011110100110001001100000011000000110000 -
#17000
b1101 $
b1101 *
b1011 %
b1011 )
b100000101010011010100100011000100100000010000010011110100110001001100000011000000110001 -
#18000
b1111 $
b1111 *
b1111 %
b1111 )
b1101 +
b1101 ,
b100000101010011010100100011000100100000010000010011110100110001001100000011000100110001 -
#19000
b1111 +
b1111 ,
b100000101010011010100100011000100100000010000010011110100110001001100010011000100110001 -
