step-2/verilog/arithmetic_step2.v
`timescale 1ns/1ps

// 4-bit Adder with carry in and carry out
module add4 (
    input  wire [3:0] a,
    input  wire [3:0] b,
    input  wire       cin,
    output wire [3:0] y,
    output wire       cout
);
    assign {cout, y} = a + b + cin;
endmodule

// 4-bit Subtractor with borrow out
module sub4 (
    input  wire [3:0] a,
    input  wire [3:0] b,
    output wire [3:0] y,
    output wire       bout
);
    assign {bout, y} = a - b;
endmodule

// 4-bit Multiplier
module mul4 (
    input  wire [3:0] a,
    input  wire [3:0] b,
    output wire [7:0] y
);
    assign y = a * b;
endmodule

// 4-bit Divider
module div4 (
    input  wire [3:0] a,
    input  wire [3:0] b,
    output wire [3:0] y,
    output wire [3:0] rem
);
    assign y = a / b;
    assign rem = a % b;
endmodule

step-2/tests/tb_arithmetic_step2.v
`timescale 1ns/1ps

module tb_arithmetic_step2;

  reg [3:0] a, b;
  reg cin;
  wire [3:0] y_add, y_sub, y_div, y_rem;
  wire [7:0] y_mul;
  wire cout, bout;

  integer errors;

  add4 add4_dut (.a(a), .b(b), .cin(cin), .y(y_add), .cout(cout));
  sub4 sub4_dut (.a(a), .b(b), .y(y_sub), .bout(bout));
  mul4 mul4_dut (.a(a), .b(b), .y(y_mul));
  div4 div4_dut (.a(a), .b(b), .y(y_div), .rem(y_rem));

  task check;
    input [255:0] label;
    input signed [31:0] got;
    input signed [31:0] exp;
    begin
      if (got !== exp) begin
        $display("FAIL: %s | got=%d exp=%d", label, got, exp);
        errors = errors + 1;
      end else begin
        $display("PASS: %s", label);
      end
    end
  endtask

  initial begin
    errors = 0;
    $dumpfile("waves/arithmetic_step2.vcd");
    $dumpvars(0, tb_arithmetic_step2);

    // Test ADD
    a=4'd5; b=4'd3; cin=0; #5; check("ADD", {1'b0, cout, y_add}, 8);
    a=4'd9; b=4'd8; cin=1; #5; check("ADD", {1'b0, cout, y_add}, 18);

    // Test SUB
    a=4'd5; b=4'd3; #5; check("SUB", y_sub, 2);
    a=4'd3; b=4'd5; #5; check("SUB", $signed(y_sub), -2);

    // Test MUL
    a=4'd5; b=4'd3; #5; check("MUL", y_mul, 15);
    a=4'd9; b=4'd8; #5; check("MUL", y_mul, 72);

    // Test DIV
    a=4'd7; b=4'd3; #5; check("DIV", {y_div, y_rem}, 8'b0010_0001); // 7/3 = 2 rem 1
    a=4'd15; b=4'd4; #5; check("DIV", {y_div, y_rem}, 8'b0011_0011); // 15/4 = 3 rem 3

    if (errors == 0) $display("ARITHMETIC_STEP2: ALL TESTS PASSED ✅");
    else             $display("ARITHMETIC_STEP2: FAILED ❌ errors=%0d", errors);

    #5; $finish;
  end

endmodule

step-2/waves/arithmetic_step2.vcd
$date
	Mon Mar 30 11:50:16 2026
$end
$version
	Icarus Verilog
$end
$timescale
	1ps
$end
$scope module tb_arithmetic_step2 $end
$var wire 4 ! y_sub [3:0] $end
$var wire 4 " y_rem [3:0] $end
$var wire 8 # y_mul [7:0] $end
$var wire 4 $ y_div [3:0] $end
$var wire 4 % y_add [3:0] $end
$var wire 1 & cout $end
$var wire 1 ' bout $end
$var reg 4 ( a [3:0] $end
$var reg 4 ) b [3:0] $end
$var reg 1 * cin $end
$var integer 32 + errors [31:0] $end
$scope module add4_dut $end
$var wire 4 , a [3:0] $end
$var wire 4 - b [3:0] $end
$var wire 1 * cin $end
$var wire 4 . y [3:0] $end
$var wire 1 & cout $end
$upscope $end
$scope module div4_dut $end
$var wire 4 / a [3:0] $end
$var wire 4 0 b [3:0] $end
$var wire 4 1 y [3:0] $end
$var wire 4 2 rem [3:0] $end
$upscope $end
$scope module mul4_dut $end
$var wire 4 3 a [3:0] $end
$var wire 4 4 b [3:0] $end
$var wire 8 5 y [7:0] $end
$upscope $end
$scope module sub4_dut $end
$var wire 4 6 a [3:0] $end
$var wire 4 7 b [3:0] $end
$var wire 4 8 y [3:0] $end
$var wire 1 ' bout $end
$upscope $end
$scope task check $end
$var reg 32 9 exp [31:0] $end
$var reg 32 : got [31:0] $end
$var reg 256 ; label [255:0] $end
$upscope $end
$upscope $end
$enddefinitions $end
$comment Show the parameter values. $end
$dumpall
$end
#0
$dumpvars
bx ;
bx :
bx 9
b10 8
b11 7
b101 6
b1111 5
b11 4
b101 3
b10 2
b1 1
b11 0
b101 /
b1000 .
b11 -
b101 ,
b0 +
0*
b11 )
b101 (
0'
0&
b1000 %
b1 $
b1111 #
b10 "
b10 !
$end
#5000
1&
b10 %
b10 .
b1 !
b1 8
1*
b1000 )
b1000 -
b1000 0
b1000 4
b1000 7
b1 $
b1 1
b1 "
b1 2
b1001000 #
b1001000 5
b1001 (
b1001 ,
b1001 /
b1001 3
b1001 6
b1000 9
b1000 :
b10000010100010001000100 ;
#10000
b1001 %
b1001 .
0&
b10 !
b10 8
b11 )
b11 -
b11 0
b11 4
b11 7
b1 $
b1 1
b10 "
b10 2
b1111 #
b1111 5
b101 (
b101 ,
b101 /
b101 3
b101 6
b10010 9
b10010 :
#15000
1'
b1110 !
b1110 8
b0 $
b0 1
b101 )
b101 -
b101 0
b101 4
b101 7
b11 "
b11 2
b1111 #
b1111 5
b11 (
b11 ,
b11 /
b11 3
b11 6
b10 9
b10 :
b10100110101010101000010 ;
#20000
b10 !
b10 8
0'
b11 )
b11 -
b11 0
b11 4
b11 7
b1 $
b1 1
b10 "
b10 2
b1111 #
b1111 5
b101 (
b101 ,
b101 /
b101 3
b101 6
b11111111111111111111111111111110 9
b11111111111111111111111111111110 :
#25000
1&
b10 %
b10 .
b1 !
b1 8
b1000 )
b1000 -
b1000 0
b1000 4
b1000 7
b1 $
b1 1
b1 "
b1 2
b1001000 #
b1001000 5
b1001 (
b1001 ,
b1001 /
b1001 3
b1001 6
b1111 9
b1111 :
b10011010101010101001100 ;
#30000
0&
b1011 %
b1011 .
b100 !
b100 8
b11 )
b11 -
b11 0
b11 4
b11 7
b10 $
b10 1
b1 "
b1 2
b10101 #
b10101 5
b111 (
b111 ,
b111 /
b111 3
b111 6
b1001000 9
b1001000 :
#35000
b100 %
b100 .
1&
b1011 !
b1011 8
b100 )
b100 -
b100 0
b100 4
b100 7
b11 $
b11 1
b11 "
b11 2
b111100 #
b111100 5
b1111 (
b1111 ,
b1111 /
b1111 3
b1111 6
b100001 9
b100001 :
b10001000100100101010110 ;
#40000
b110011 9
b110011 :
